LICENSE
MANIFEST.in
README.md
setup.py
pyDetectRight/DetectRight.py
pyDetectRight/__init__.py
pyDetectRight.egg-info/PKG-INFO
pyDetectRight.egg-info/SOURCES.txt
pyDetectRight.egg-info/dependency_links.txt
pyDetectRight.egg-info/top_level.txt
pyDetectRight/java/lib/commons-codec-1.8.jar
pyDetectRight/java/lib/commons-collections-3.2.1.jar
pyDetectRight/java/lib/detectright.jar
pyDetectRight/java/lib/py4j0.7.jar
pyDetectRight/java/lib/sqlite-jdbc-3.7.2.jar
pyDetectRight/java/src/omnilab/bd/chenxm/DetectRightEntry.java